MANIFEST.in
README.md
setup.py
aa_statistics.egg-info/PKG-INFO
aa_statistics.egg-info/SOURCES.txt
aa_statistics.egg-info/dependency_links.txt
aa_statistics.egg-info/requires.txt
aa_statistics.egg-info/top_level.txt
aastatistics/__init__.py
aastatistics/admin.py
aastatistics/app_settings.py
aastatistics/apps.py
aastatistics/auth_hooks.py
aastatistics/filters.py
aastatistics/models.py
aastatistics/tasks.py
aastatistics/test.py
aastatistics/urls.py
aastatistics/views.py
aastatistics/migrations/0001_initial.py
aastatistics/migrations/0002_auto_20210106_0803.py
aastatistics/migrations/0003_auto_20210715_1031.py
aastatistics/migrations/0004_add_date_strs.py
aastatistics/migrations/0005_alter_zkillmonth_date_str.py
aastatistics/migrations/0006_auto_20210715_1048.py
aastatistics/migrations/__init__.py
aastatistics/templatetags/__init__.py
aastatistics/templatetags/statistics_tags.py
tests/__init__.py
tests/celery.py
tests/test_settings.py
tests/urls.py
tests/views.py